Metadata-Version: 2.4
Name: inference-core
Version: 0.64.6
Summary: With no prior knowledge of machine learning or device-specific deployment, you can deploy a computer vision model to a range of devices and environments using Roboflow Inference.
Home-page: https://github.com/roboflow/inference
Author: Roboflow
Author-email: help@roboflow.com
Classifier: Development Status :: 5 - Production/Stable
Classifier: Intended Audience :: Developers
Classifier: Intended Audience :: Education
Classifier: Intended Audience :: Science/Research
Classifier: License :: OSI Approved :: Apache Software License
Classifier: Programming Language :: Python :: 3
Classifier: Programming Language :: Python :: 3 :: Only
Classifier: Topic :: Software Development
Classifier: Topic :: Scientific/Engineering
Classifier: Topic :: Scientific/Engineering :: Artificial Intelligence
Classifier: Topic :: Scientific/Engineering :: Image Recognition
Classifier: Typing :: Typed
Classifier: Operating System :: OS Independent
Requires-Python: >=3.9,<3.13
License-File: LICENSE
License-File: LICENSE.core
Requires-Dist: aiortc>=1.9.0
Requires-Dist: av==14.2.0
Requires-Dist: APScheduler<4.0.0,>=3.10.1
Requires-Dist: asyncua~=1.1.5
Requires-Dist: cachetools<6.0.0
Requires-Dist: cython~=3.0.0
Requires-Dist: python-dotenv~=1.0.0
Requires-Dist: fastapi<0.116,>=0.100
Requires-Dist: numpy<2.4.0,>=2.0.0
Requires-Dist: opencv-python<=4.10.0.84,>=4.8.1.78
Requires-Dist: opencv-contrib-python<=4.10.0.84,>=4.8.1.78
Requires-Dist: pillow<12.0,>=11.0
Requires-Dist: prometheus-fastapi-instrumentator<=6.0.0
Requires-Dist: psutil>=7.0.0
Requires-Dist: redis~=5.0.0
Requires-Dist: requests<3.0.0,>=2.32.0
Requires-Dist: rich<15.0.0,>=13.0.0
Requires-Dist: supervision>=0.27
Requires-Dist: pybase64~=1.0.0
Requires-Dist: scikit-image<=0.25.2,>=0.19.0
Requires-Dist: requests-toolbelt~=1.0.0
Requires-Dist: wheel<=0.45.1,>=0.38.1
Requires-Dist: setuptools>=70.0.0
Requires-Dist: networkx<4.0.0,>=3.0.0
Requires-Dist: pydantic<2.12.0,>=2.8.0
Requires-Dist: pydantic-settings<2.8
Requires-Dist: openai<2.0.0,>=1.12.0
Requires-Dist: structlog<25.0.0,>=24.1.0
Requires-Dist: zxing-cpp~=2.2.0
Requires-Dist: boto3<=1.41.5,>=1.40.0
Requires-Dist: botocore<=1.41.5,>=1.40.0
Requires-Dist: typing_extensions<=4.12.2,>=4.8.0
Requires-Dist: pydot~=2.0.0
Requires-Dist: shapely<2.1.0,>=2.0.4
Requires-Dist: tldextract~=5.1.2
Requires-Dist: packaging~=24.0
Requires-Dist: anthropic~=0.49.0
Requires-Dist: pandas<3.0.0,>=2.2.3
Requires-Dist: paho-mqtt~=1.6.1
Requires-Dist: pytest<9.0.0,>=8.0.0
Requires-Dist: tokenizers<0.23.0,>=0.19.0
Requires-Dist: slack-sdk~=3.33.4
Requires-Dist: twilio~=9.3.7
Requires-Dist: httpx~=0.28.1
Requires-Dist: pylogix==1.0.5
Requires-Dist: pymodbus<=3.8.3,>=3.6.9
Requires-Dist: backoff~=2.2.0
Requires-Dist: filelock<=3.17.0,>=3.12.0
Requires-Dist: onvif-zeep-async==2.0.0
Requires-Dist: simple-pid~=2.0.1
Requires-Dist: qrcode~=8.0.0
Requires-Dist: inference-models>=0.17.3
Requires-Dist: requests<3.0.0,>=2.32.0
Requires-Dist: docker<8.0.0,>=7.0.0
Requires-Dist: click<8.2.0
Requires-Dist: typer<=0.16.0,>=0.9.0
Requires-Dist: rich<15.0.0,>=13.0.0
Requires-Dist: PyYAML~=6.0.0
Requires-Dist: supervision>=0.26
Requires-Dist: opencv-python<=4.10.0.84,>=4.8.1.78
Requires-Dist: tqdm<5.0.0,>=4.0.0
Requires-Dist: nvidia-ml-py<13.0.0
Requires-Dist: py-cpuinfo~=9.0.0
Requires-Dist: aiohttp<=3.10.11,>=3.9.0
Requires-Dist: backoff~=2.2.0
Requires-Dist: pandas<3.0.0,>=2.2.3
Requires-Dist: pybase64~=1.0.0
Requires-Dist: pydantic<2.12.0,>=2.8.0
Requires-Dist: requests<3.0.0,>=2.32.0
Requires-Dist: dataclasses-json~=0.6.0
Requires-Dist: opencv-python<=4.10.0.84,>=4.8.1.78
Requires-Dist: pillow<12.0,>=11.0
Requires-Dist: supervision>=0.26
Requires-Dist: numpy<2.4.0,>=2.0.0
Requires-Dist: aiohttp<=3.10.11,>=3.9.0
Requires-Dist: backoff~=2.2.0
Requires-Dist: py-cpuinfo~=9.0.0
Provides-Extra: clip
Requires-Dist: rf-clip==1.1; extra == "clip"
Provides-Extra: easy-ocr
Requires-Dist: easyocr==1.7.2; extra == "easy-ocr"
Provides-Extra: cpu
Requires-Dist: onnxruntime<1.22.0,>=1.15.1; extra == "cpu"
Requires-Dist: nvidia-ml-py<13.0.0; extra == "cpu"
Provides-Extra: gaze
Requires-Dist: rf-mediapipe<0.11,>=0.9; extra == "gaze"
Provides-Extra: gpu
Requires-Dist: onnxruntime-gpu<1.22.0,>=1.15.1; extra == "gpu"
Provides-Extra: grounding-dino
Requires-Dist: rf_groundingdino<=0.3.0,>=0.2.0; extra == "grounding-dino"
Provides-Extra: hosted
Requires-Dist: pymemcache~=4.0.0; extra == "hosted"
Requires-Dist: elasticache_auto_discovery~=1.0.0; extra == "hosted"
Provides-Extra: http
Requires-Dist: uvicorn[standard]<=0.34.0; extra == "http"
Requires-Dist: python-multipart==0.0.19; extra == "http"
Requires-Dist: fastapi-cprofile<=0.0.2; extra == "http"
Requires-Dist: orjson<=3.10.11,>=3.9.10; extra == "http"
Requires-Dist: asgi_correlation_id~=4.3.1; extra == "http"
Provides-Extra: sam
Requires-Dist: rf-segment-anything==1.0; extra == "sam"
Requires-Dist: rf-sam-2==1.0.2; extra == "sam"
Requires-Dist: rasterio~=1.4.0; extra == "sam"
Requires-Dist: pycocotools>=2.0.10; extra == "sam"
Requires-Dist: torch<2.7.0,>=2.0.1; extra == "sam"
Requires-Dist: torchvision>=0.15.2; extra == "sam"
Provides-Extra: yolo-world
Requires-Dist: ultralytics<=8.3.40,>=8.1.27; extra == "yolo-world"
Requires-Dist: dill==0.3.8; extra == "yolo-world"
Requires-Dist: rf-clip==1.1; extra == "yolo-world"
Provides-Extra: transformers
Requires-Dist: torch<2.7.0,>=2.0.1; extra == "transformers"
Requires-Dist: torchvision>=0.15.0; extra == "transformers"
Requires-Dist: transformers<5.0.0,>=4.57.3; extra == "transformers"
Requires-Dist: timm<1.0.23; extra == "transformers"
Requires-Dist: accelerate<2.0.0,>=1.0.0; extra == "transformers"
Requires-Dist: einops<=0.8.0,>=0.7.0; extra == "transformers"
Requires-Dist: peft~=0.15.0; extra == "transformers"
Requires-Dist: num2words~=0.5.14; extra == "transformers"
Requires-Dist: bitsandbytes<0.46.0,>=0.42.0; extra == "transformers"
Requires-Dist: num2words~=0.5.14; extra == "transformers"
Requires-Dist: pyvips[binary]>=2.2.3; extra == "transformers"
Dynamic: author
Dynamic: author-email
Dynamic: classifier
Dynamic: description
Dynamic: description-content-type
Dynamic: home-page
Dynamic: license-file
Dynamic: provides-extra
Dynamic: requires-dist
Dynamic: requires-python
Dynamic: summary
